augint_test/__init__.py
augint_test/print_hi.py
augint_test-1.15.0.dist-info/LICENSE
augint_test-1.15.0.dist-info/METADATA
augint_test-1.15.0.dist-info/WHEEL
augint_test-1.15.0.dist-info/entry_points.txt
augint_test-1.15.0.dist-info/RECORD
