Metadata-Version: 2.3
Name: augint-test
Version: 1.15.0
Summary: 
License: Copyright (c) Augmenting Integrations LLC
Author: Samuel Vange
Author-email: 7166607+svange@users.noreply.github.com
Requires-Python: >=3.12,<4.0
Classifier: License :: Other/Proprietary License
Classifier: Programming Language :: Python :: 3
Classifier: Programming Language :: Python :: 3.12
Classifier: Programming Language :: Python :: 3.13
